mit_semseg/__init__.py
mit_semseg/dataset.py
mit_semseg/utils.py
mit_semseg/config/__init__.py
mit_semseg/config/defaults.py
mit_semseg/lib/__init__.py
mit_semseg/lib/nn/__init__.py
mit_semseg/lib/nn/modules/__init__.py
mit_semseg/lib/nn/modules/batchnorm.py
mit_semseg/lib/nn/modules/comm.py
mit_semseg/lib/nn/modules/replicate.py
mit_semseg/lib/nn/modules/unittest.py
mit_semseg/lib/nn/modules/tests/__init__.py
mit_semseg/lib/nn/modules/tests/test_numeric_batchnorm.py
mit_semseg/lib/nn/modules/tests/test_sync_batchnorm.py
mit_semseg/lib/nn/parallel/__init__.py
mit_semseg/lib/nn/parallel/data_parallel.py
mit_semseg/lib/utils/__init__.py
mit_semseg/lib/utils/th.py
mit_semseg/lib/utils/data/__init__.py
mit_semseg/lib/utils/data/dataloader.py
mit_semseg/lib/utils/data/dataset.py
mit_semseg/lib/utils/data/distributed.py
mit_semseg/lib/utils/data/sampler.py
mit_semseg/models/__init__.py
mit_semseg/models/hrnet.py
mit_semseg/models/mobilenet.py
mit_semseg/models/models.py
mit_semseg/models/resnet.py
mit_semseg/models/resnext.py
mit_semseg/models/utils.py
mit_semseg-1.0.0.dist-info/LICENSE
mit_semseg-1.0.0.dist-info/METADATA
mit_semseg-1.0.0.dist-info/WHEEL
mit_semseg-1.0.0.dist-info/top_level.txt
mit_semseg-1.0.0.dist-info/RECORD
