Metadata-Version: 2.1
Name: mit-semseg
Version: 1.0.0
Summary: Pytorch implementation for Semantic Segmentation/Scene Parsing on MIT ADE20K dataset
Home-page: https://github.com/CSAILVision/semantic-segmentation-pytorch
Author: MIT CSAIL
License: UNKNOWN
Platform: UNKNOWN
Classifier: Programming Language :: Python :: 3
Classifier: License :: OSI Approved :: BSD License
Classifier: Operating System :: OS Independent
Requires-Dist: numpy
Requires-Dist: torch (>=0.4.1)
Requires-Dist: torchvision
Requires-Dist: opencv-python
Requires-Dist: yacs
Requires-Dist: scipy
Requires-Dist: tqdm
